LICENSE
hook/__init__.py
hook/openapi_substituter.py
sceptre_openapi_substitution_hook-0.0.1.dist-info/LICENSE
sceptre_openapi_substitution_hook-0.0.1.dist-info/METADATA
sceptre_openapi_substitution_hook-0.0.1.dist-info/WHEEL
sceptre_openapi_substitution_hook-0.0.1.dist-info/entry_points.txt
sceptre_openapi_substitution_hook-0.0.1.dist-info/RECORD
