Metadata-Version: 2.1
Name: sceptre-openapi-substitution-hook
Version: 0.0.1
Summary: A Sceptre hook for resolving variables in openapi definitions.
Home-page: https://github.com/nicholasphair/sceptre-openapi-substitution-hook
License: Apache-2.0
Keywords: sceptre,sceptre-hook,openapi
Author: Nicholas Phair
Author-email: np4ay@viginia.edu
Requires-Python: >=3.8,<3.12
Classifier: Environment :: Console
Classifier: Intended Audience :: Developers
Classifier: License :: OSI Approved :: Apache Software License
Classifier: Natural Language :: English
Classifier: Programming Language :: Python :: 3
Classifier: Programming Language :: Python :: 3.8
Classifier: Programming Language :: Python :: 3.9
Classifier: Programming Language :: Python :: 3.10
Classifier: Programming Language :: Python :: 3.11
Project-URL: Repository, https://github.com/nicholasphair/sceptre-openapi-substitution-hook
